solv_ai/__init__.py
solv_ai/bn_folding.py
solv_ai/distributed_computing.py
solv_ai/dynamic_quantization.py
solv_ai/efficient_models.py
solv_ai/knowledge_distillation.py
solv_ai/layer_fusion.py
solv_ai/layer_management.py
solv_ai/memory_management.py
solv_ai/mixed_precision.py
solv_ai/pruning.py
solv_ai/quantization.py
solv_ai/utils.py
solv_ai/weight_sharing.py
solv_ai-0.2.5.dist-info/LICENSE
solv_ai-0.2.5.dist-info/METADATA
solv_ai-0.2.5.dist-info/WHEEL
solv_ai-0.2.5.dist-info/top_level.txt
solv_ai-0.2.5.dist-info/RECORD
