Metadata-Version: 2.1
Name: solv-ai
Version: 0.2.5
Summary: A high-performance AI model optimization library
Home-page: https://github.com/CloudSolv-AI/solv-ai
Author: CloudSolv AI
Author-email: eric@cloudsolv.co
Classifier: Programming Language :: Python :: 3
Classifier: License :: OSI Approved :: MIT License
Classifier: Operating System :: OS Independent
Requires-Python: >=3.6
License-File: LICENSE
Requires-Dist: numpy <2.0.0,>=1.18.0
Requires-Dist: torch <2.5.0,>=1.6.0
Requires-Dist: torchvision <1.0.0,>=0.7.0
